MANIFEST.in
README.md
setup.py
onnx_vis/__init__.py
onnx_vis/__main__.py
onnx_vis/onnx_vis.py
onnx_vis.egg-info/PKG-INFO
onnx_vis.egg-info/SOURCES.txt
onnx_vis.egg-info/dependency_links.txt
onnx_vis.egg-info/entry_points.txt
onnx_vis.egg-info/requires.txt
onnx_vis.egg-info/top_level.txt
onnx_vis/static/index.html
onnx_vis/static/onnxai-icon.svg
onnx_vis/static/assets/index-4c5da1dc.js
onnx_vis/static/assets/index-64a7f604.css