Metadata-Version: 2.1
Name: onnx-vis
Version: 1.0.11
Summary: This package help you visualize the ONNX model graph. Client-Server based architecture lets you share the model, using just a url instead of sharing the entire model.
Home-page: https://github.com/sleepingsaint/onnx_visualizer
Author: sleepingsaint
Author-email: suryasantosh14523@gmail.com
License: MIT
Keywords: example documentation tutorial
Platform: UNKNOWN
Classifier: Topic :: Utilities
Classifier: License :: OSI Approved :: MIT License
